thermostat/__init__.py
thermostat/climate_zone.py
thermostat/core.py
thermostat/eeweather_wrapper.py
thermostat/exporters.py
thermostat/importers.py
thermostat/multiple.py
thermostat/parallel.py
thermostat/regression.py
thermostat/stations.py
thermostat/stats.py
thermostat/resources/Building America Climate Zone to Zipcode Database_Rev2_2016.09.08.csv
thermostat/resources/NationalAverageClimateZoneWeightings.csv
thermostat/resources/__init__.py
thermostat/resources/regional_baselines.csv
thermostat/resources/zipcode_usaf_station.json
thermostat/util/__init__.py
thermostat/util/testing.py
thermostat-1.7.0.dist-info/METADATA
thermostat-1.7.0.dist-info/RECORD
thermostat-1.7.0.dist-info/WHEEL
thermostat-1.7.0.dist-info/top_level.txt
