Metadata-Version: 2.1
Name: thermostat
Version: 1.7.0
Summary: Calculate connected thermostat savings
Home-page: https://github.com/EPAENERGYSTAR/epathermostat
Author: Phil Ngo
Author-email: UNKNOWN
License: MIT
Keywords: thermostat savings EPA
Platform: UNKNOWN
Classifier: Development Status :: 4 - Beta
Classifier: License :: OSI Approved :: MIT License
Classifier: Programming Language :: Python :: 2
Classifier: Programming Language :: Python :: 3
Requires-Dist: eemeter (==2.5.2)
Requires-Dist: eeweather (==0.3.13)
Requires-Dist: pandas (==0.22.0)
Requires-Dist: sqlalchemy (==1.3.1)
